axeprofiler/__init__.py
axeprofiler/__main__.py
axeprofiler/api.py
axeprofiler/cli.py
axeprofiler/profiles.py
axeprofiler/utils.py
axeprofiler-1.1.5.dist-info/METADATA
axeprofiler-1.1.5.dist-info/WHEEL
axeprofiler-1.1.5.dist-info/entry_points.txt
axeprofiler-1.1.5.dist-info/licenses/COPYING
axeprofiler-1.1.5.dist-info/RECORD
