Metadata-Version: 2.4
Name: AxeProfiler
Version: 1.1.5
Summary: Axeprofiler provides a convenient CLI to create/save/apply AxeOS miner configs.
Project-URL: Homepage, https://github.com/Celshade/AxeProfiler
Author-email: Celshade <ggcelshade@gmail.com>
License-File: COPYING
Keywords: axeos,bitaxe,bitcoin,miner,nerdaxe,nerdqaxe
Classifier: Development Status :: 4 - Beta
Classifier: Intended Audience :: Developers
Classifier: Programming Language :: Python :: 3.11
Classifier: Topic :: Software Development :: User Interfaces
Classifier: Topic :: System :: Distributed Computing
Requires-Python: >=3.11
Requires-Dist: requests>=2.32.5
Requires-Dist: rich>=14.2.0
